{
  "strategy_type": "branching_program_advanced",
  "generation_timestamp": "2025-07-10T17:45:00Z",
  "algorithm": "advanced_pebbling_with_branching_programs",
  "optimization_score": 28.028278779781786,
  "memory_efficiency": {
    "peak_memory_mb": 35,
    "memory_timeline": [
      [
        0,
        10
      ],
      [
        1,
        0
      ],
      [
        1,
        25
      ],
      [
        16,
        0
      ],
      [
        16,
        15
      ],
      [
        21,
        0
      ],
      [
        21,
        20
      ],
      [
        29,
        0
      ],
      [
        29,
        18
      ],
      [
        35,
        0
      ],
      [
        35,
        12
      ],
      [
        39,
        0
      ],
      [
        39,
        30
      ],
      [
        51,
        0
      ],
      [
        51,
        35
      ],
      [
        71,
        0
      ],
      [
        71,
        8
      ],
      [
        74,
        0
      ],
      [
        74,
        5
      ],
      [
        75,
        0
      ]
    ],
    "optimization_ratio": 28.571
  },
  "execution_plan": {
    "optimal_order": [
      "env_setup",
      "prd_gen",
      "dep_analysis",
      "sqrt_opt",
      "tree_opt",
      "pebbling",
      "catalytic",
      "evolution",
      "validation",
      "monitoring"
    ],
    "total_phases": 10,
    "estimated_duration": 365
  },
  "resource_management": {
    "conflicts_detected": 0,
    "conflict_details": [],
    "resolution_strategy": "temporal_separation_with_priority_queuing"
  },
  "advanced_features": {
    "branching_program_optimization": true,
    "memory_pressure_analysis": true,
    "dependency_aware_scheduling": true,
    "resource_contention_resolution": true,
    "adaptive_priority_calculation": true
  },
  "performance_metrics": {
    "memory_utilization_efficiency": "92.3%",
    "temporal_optimization": "87.6%",
    "conflict_minimization": "94.1%",
    "overall_strategy_score": 28.03
  }
}